dotnetz/System/Disposable.py
dotnetz/System/EventArgs.py
dotnetz/System/EventHandler.py
dotnetz/System/IDisposable.py
dotnetz/System/__init__.py
dotnetz/__init__.py
dotnetz/runtime.py
dotnetz-0.1.2.dist-info/LICENSE
dotnetz-0.1.2.dist-info/WHEEL
dotnetz-0.1.2.dist-info/METADATA
dotnetz-0.1.2.dist-info/RECORD
